Workbook

Sheet Company Shortlist
A1: SIWES / IT Placement Tracker – 2027
A2: Research snapshot: 30 October 2026. 'Not confirmed' means no reliable public confirmation found; verify directly before making relocation or eligibility decisions.
A4: Ranking | B4: Organisation name | C4: Industry | D4: Office location | E4: Relevant departments for my career interests | F4: Does the company accept SIWES students? | G4: Does it accept six-month placements? | H4: Minimum CGPA requirement | I4: Monthly SIWES stipend | J4: Accommodation provided? | K4: Transport allowance or shuttle? | L4: Feeding or meal benefits? | M4: Application opening date | N4: Application deadline | O4: Official careers website | P4: HR/recruitment contact | Q4: Current application status | R4: Overall suitability rating out of 10 | S4: Notes and next steps | T4: OAU Students Accepted? | U4: Analytics-Related Role Available? | V4: Official SIWES Vacancy?
A5: 1 | B5: Seplat Energy | C5: Energy | D5: Lagos / operational locations | E5: Business intelligence; data analytics; commercial; strategy; finance | F5: Yes – official undergraduate internship scheme; SIWES letter from HOD required | G5: Yes – official page states 3, 6 or 12 months | H5: Not confirmed | I5: Not confirmed | J5: Not confirmed | K5: Not confirmed | L5: Not confirmed | M5: Not announced for 2027 | N5: Not announced for 2027 | O5: https://www.seplatenergy.com/careers/career-opportunities/ | P5: recruitment@seplatenergy.com (published general recruitment contact) | Q5: Not Started | R5: 9 | S5: Official source confirms undergraduate internship scheme and 3/6/12-month durations. Specific analytics placement, OAU acceptance, CGPA, stipend and relocation benefits are not confirmed. Six-month SIWES route makes this the strongest first enquiry. | T5: Not confirmed | U5: Not confirmed | V5: Programme page exists; 2027 SIWES vacancy not announced
A6: 2 | B6: NielsenIQ (NIQ) | C6: Market research / data analytics | D6: Lagos (Nigeria roles appear on global jobs site) | E6: Consumer insights; analytics; data science & BI; client service; research | F6: Not confirmed – current Lagos intern listing is not proof of SIWES acceptance | G6: Not confirmed | H6: Not confirmed | I6: Not confirmed | J6: Not confirmed | K6: Not confirmed | L6: Not confirmed | M6: Not announced for 2027 | N6: Not announced for 2027 | O6: https://nielseniq.com/global/en/jobs/ | P6: Apply through official jobs portal | Q6: Not Started | R6: 9 | S6: Official jobs portal lists Analytics and Data Science & Business Intelligence job teams; a Lagos Intern listing appeared, but the listing is not confirmed as SIWES or analytics. Ask about six-month attachment, OAU, department and support. | T6: Not confirmed | U6: Not confirmed | V6: Not confirmed
A7: 3 | B7: Kantar | C7: Market research / consulting | D7: Nigeria location to confirm per vacancy | E7: Analytics; data science; research; strategic consultancy; client management | F7: Not confirmed – general early-career opportunities are not proof of SIWES acceptance | G7: Not confirmed | H7: Not confirmed | I7: Not confirmed | J7: Not confirmed | K7: Not confirmed | L7: Not confirmed | M7: Not announced for 2027 | N7: Not announced for 2027 | O7: https://careers.kantar.com/ | P7: Use official careers portal | Q7: Not Started | R7: 8 | S7: Strong consumer insights / marketing analytics fit. No Nigeria-specific SIWES or six-month placement confirmed from official careers information. Ask about an industrial attachment. | T7: Not confirmed | U7: Not confirmed | V7: Not confirmed
A8: 4 | B8: Interswitch | C8: Fintech / technology | D8: Lagos | E8: Data analytics; BI; product; business analysis; strategy; operations | F8: Not confirmed | G8: Not confirmed | H8: Not confirmed | I8: Not confirmed | J8: Not confirmed | K8: Not confirmed | L8: Not confirmed | M8: Not announced for 2027 | N8: Not announced for 2027 | O8: https://interswitchgroup.com/company/careers | P8: Official careers portal / Talent Community | Q8: Not Started | R8: 8 | S8: Strong fintech / BI / product analytics fit, but official careers page reviewed does not confirm SIWES or six-month placements. Do not assume general vacancies are SIWES. | T8: Not confirmed | U8: Not confirmed | V8: Not confirmed
A9: 5 | B9: MTN Nigeria | C9: Telecommunications | D9: Ikoyi, Lagos | E9: Business intelligence; data analytics; marketing; customer insights; strategy; technology | F9: Not confirmed – general careers and graduate programme information is not SIWES confirmation | G9: Not confirmed | H9: Not confirmed | I9: Not confirmed | J9: Not confirmed | K9: Not confirmed | L9: Not confirmed | M9: Not announced for 2027 | N9: Not announced for 2027 | O9: https://www.mtn.ng/career/ | P9: Official careers portal | Q9: Not Started | R9: 8 | S9: Strong analytics, customer and commercial exposure potential. Official careers pages do not confirm a six-month SIWES route, OAU acceptance or support benefits. | T9: Not confirmed | U9: Not confirmed | V9: Not confirmed
A10: 6 | B10: Nestlé Nigeria | C10: FMCG / manufacturing | D10: Lagos; factory locations to confirm | E10: Consumer insights; sales analytics; marketing; supply chain analytics; finance; business planning | F10: Not confirmed for Nigeria SIWES – Nestlé confirms internships globally, not a specific OAU SIWES route | G10: Not confirmed | H10: Not confirmed | I10: Paid internships confirmed generally; Nigeria-specific stipend not stated | J10: Not confirmed | K10: Not confirmed | L10: Not announced for 2027 | M10: Not announced for 2027 | N10: Not announced for 2027 | O10: https://www.nestle.com/jobs/students-graduates | P10: Official Nestlé careers / students page | Q10: Not Started | R10: 8 | S10: Nestlé official FAQ confirms internships are paid and run across locations; this does not verify a Nigeria SIWES vacancy, six-month duration, stipend amount or relocation benefits. Strong consumer / commercial analytics fit. | T10: Not confirmed | U10: Not confirmed | V10: Not confirmed
A11: 7 | B11: Nigerian Bottling Company | C11: FMCG / beverages | D11: Lagos; plant locations to confirm | E11: Commercial analytics; sales; marketing; supply chain; finance; consumer insights | F11: Not confirmed | G11: Not confirmed | H11: Not confirmed | I11: Not confirmed | J11: Not confirmed | K11: Not confirmed | L11: Not confirmed | M11: Not announced for 2027 | N11: Not announced for 2027 | O11: https://www.coca-colahellenic.com/ | P11: Use official group careers portal; verify Nigeria-specific entity and vacancies | Q11: Not Started | R11: 7 | S11: Potential FMCG commercial / sales analytics and consumer exposure. SIWES route, six-month duration and benefits not confirmed. | T11: Not confirmed | U11: Not confirmed | V11: Not confirmed
A12: 8 | B12: The Coca-Cola Company | C12: Beverages / consumer goods | D12: Nigeria role location to confirm | E12: Marketing; consumer insights; commercial; strategy; analytics | F12: Not confirmed | G12: Not confirmed | H12: Not confirmed | I12: Not confirmed | J12: Not confirmed | K12: Not confirmed | L12: Not confirmed | M12: Not announced for 2027 | N12: Not announced for 2027 | O12: https://www.coca-colacompany.com/careers/early-careers | P12: Official careers portal | Q12: Not Started | R12: 7 | S12: Distinguish The Coca-Cola Company from Nigerian Bottling Company / bottling partners. Global early-career roles do not confirm Nigeria SIWES. | T12: Not confirmed | U12: Not confirmed | V12: Not confirmed
A13: 10 | B13: Deloitte Nigeria | C13: Professional services / consulting | D13: Lagos | E13: Business analysis; consulting; data analytics; technology strategy; risk advisory | F13: Not confirmed – student / graduate opportunities are not proof of SIWES acceptance | G13: Not confirmed | H13: Some graduate/early-career roles require 2:1 and NYSC; do not apply that rule to SIWES without confirmation | I13: Not confirmed | J13: Not confirmed | K13: Not confirmed | L13: Not announced for 2027 | M13: Not announced for 2027 | N13: Not announced for 2027 | O13: https://www.deloitte.com/ng/en/careers/explore-your-fit/students.html | P13: Official student careers page / job search | Q13: Not Started | R13: 7 | S13: Good business analysis / consulting / data analytics fit, but Nigeria SIWES and six-month placement are not confirmed. Do not apply graduate trainee CGPA criteria to SIWES unless stated for that vacancy. | T13: Not confirmed | U13: Not confirmed | V13: Not confirmed
A14: 9 | B14: CWG Plc | C14: Technology / IT services | D14: Lagos | E14: Analytics; project & programme management; marketing; consulting; customer success; IT | F14: Not confirmed | G14: Not confirmed | H14: Not confirmed | I14: Not confirmed | J14: Not confirmed | K14: Not confirmed | L14: Not confirmed | M14: Not announced for 2027 | N14: Not announced for 2027 | O14: https://cwg-plc.ng/careers | P14: Official careers page | Q14: Not Started | R14: 7 | S14: Potential technology-business and analytics exposure. No verified six-month SIWES vacancy or student support confirmed. | T14: Not confirmed | U14: Not confirmed | V14: Not confirmed
A15: 11 | B15: Chevron Nigeria | C15: Energy | D15: Lagos | E15: Business analytics; commercial; finance; supply chain; technology; strategy | F15: Not confirmed | G15: Not confirmed | H15: Not confirmed | I15: Not confirmed | J15: Not confirmed | K15: Not confirmed | L15: Not confirmed | M15: Not announced for 2027 | N15: Not announced for 2027 | O15: https://careers.chevron.com/nigeria | P15: Official Nigeria careers page | Q15: Not Started | R15: 6 | S15: Potential commercial / finance / business analytics exposure, but no official undergraduate SIWES route or six-month vacancy confirmed. | T15: Not confirmed | U15: Not confirmed | V15: Not confirmed
A16: 12 | B16: Shell Nigeria | C16: Energy | D16: Lagos / other operational locations | E16: Commercial; IT; data; business support; social sciences; engineering | F16: Yes – official Nigeria SIWES programme page | G16: Not confirmed – duration not stated on the official SIWES page | H16: 3.5/5.0 for university students (official published requirement) | I16: Not confirmed | J16: Not confirmed | K16: Not confirmed | L16: Not announced for 2027 | M16: Not announced for 2027 | N16: Not announced for 2027 | O16: https://www.shell.com.ng/careers/students-and-graduates/student-industrial-training-and-internship-program.html | P16: Internshiprecruitment@shell.com (published SIWES enquiry email) | Q16: Not Started | R16: 4 | S16: Official SIWES programme confirmed for Nigerian undergraduates, including Commercial and IT disciplines. Published university CGPA minimum is 3.5/5.0, above your stated current CGPA; conditional / low-priority unless eligibility changes. Six-month duration, stipend and relocation support not confirmed. | T16: Not confirmed | U16: Not confirmed | V16: Programme page exists; 2027 SIWES vacancy not announced

Sheet Application Tracker
A1: Application Tracker
A2: Update this sheet as you research, contact recruiters and submit applications. Use the dropdowns to keep the dashboard current.
A4: Company name | B4: Date researched | C4: HR contact person's name | D4: HR email | E4: LinkedIn profile | F4: Date contacted | G4: Date application submitted | H4: Application method | I4: Documents submitted | J4: Response received? | K4: Interview date | L4: Placement duration confirmed? | M4: Stipend confirmed? | N4: Accommodation confirmed? | O4: Transport support confirmed? | P4: Department offered | Q4: Application status | R4: Follow-up date | S4: Final decision | T4: Additional notes | U4: OAU students accepted? | V4: Six-month placement confirmed? | W4: Analytics-related role confirmed? | X4: Accommodation provided? | Y4: Transport support? | Z4: Last follow-up date | AA4: Official SIWES vacancy?
A5: Seplat Energy | Q5: Not Started | U5: Not confirmed | V5: Not confirmed | W5: Not confirmed | X5: Not confirmed | Y5: Not confirmed | AA5: Not confirmed
A6: NielsenIQ (NIQ) | Q6: Not Started | U6: Not confirmed | V6: Not confirmed | W6: Not confirmed | X6: Not confirmed | Y6: Not confirmed | AA6: Not confirmed
A7: Kantar | Q7: Not Started | U7: Not confirmed | V7: Not confirmed | W7: Not confirmed | X7: Not confirmed | Y7: Not confirmed | AA7: Not confirmed
A8: Interswitch | Q8: Not Started | U8: Not confirmed | V8: Not confirmed | W8: Not confirmed | X8: Not confirmed | Y8: Not confirmed | AA8: Not confirmed
A9: MTN Nigeria | Q9: Not Started | U9: Not confirmed | V9: Not confirmed | W9: Not confirmed | X9: Not confirmed | Y9: Not confirmed | AA9: Not confirmed
A10: Nestlé Nigeria | Q10: Not Started | U10: Not confirmed | V10: Not confirmed | W10: Not confirmed | X10: Not confirmed | Y10: Not confirmed | AA10: Not confirmed
A11: Nigerian Bottling Company | Q11: Not Started | U11: Not confirmed | V11: Not confirmed | W11: Not confirmed | X11: Not confirmed | Y11: Not confirmed | AA11: Not confirmed
A12: The Coca-Cola Company | Q12: Not Started | U12: Not confirmed | V12: Not confirmed | W12: Not confirmed | X12: Not confirmed | Y12: Not confirmed | AA12: Not confirmed
A13: Deloitte Nigeria | Q13: Not Started | U13: Not confirmed | V13: Not confirmed | W13: Not confirmed | X13: Not confirmed | Y13: Not confirmed | AA13: Not confirmed
A14: CWG Plc | Q14: Not Started | U14: Not confirmed | V14: Not confirmed | W14: Not confirmed | X14: Not confirmed | Y14: Not confirmed | AA14: Not confirmed
A15: Chevron Nigeria | Q15: Not Started | U15: Not confirmed | V15: Not confirmed | W15: Not confirmed | X15: Not confirmed | Y15: Not confirmed | AA15: Not confirmed
A16: Shell Nigeria | Q16: Not Started | U16: Not confirmed | V16: Not confirmed | W16: Not confirmed | X16: Not confirmed | Y16: Not confirmed | AA16: Not confirmed
U17: Not confirmed | V17: Not confirmed | W17: Not confirmed | X17: Not confirmed | Y17: Not confirmed | AA17: Not confirmed
U18: Not confirmed | V18: Not confirmed | W18: Not confirmed | X18: Not confirmed | Y18: Not confirmed | AA18: Not confirmed
U19: Not confirmed | V19: Not confirmed | W19: Not confirmed | X19: Not confirmed | Y19: Not confirmed | AA19: Not confirmed
U20: Not confirmed | V20: Not confirmed | W20: Not confirmed | X20: Not confirmed | Y20: Not confirmed | AA20: Not confirmed
U21: Not confirmed | V21: Not confirmed | W21: Not confirmed | X21: Not confirmed | Y21: Not confirmed | AA21: Not confirmed
U22: Not confirmed | V22: Not confirmed | W22: Not confirmed | X22: Not confirmed | Y22: Not confirmed | AA22: Not confirmed
U23: Not confirmed | V23: Not confirmed | W23: Not confirmed | X23: Not confirmed | Y23: Not confirmed | AA23: Not confirmed
U24: Not confirmed | V24: Not confirmed | W24: Not confirmed | X24: Not confirmed | Y24: Not confirmed | AA24: Not confirmed
U25: Not confirmed | V25: Not confirmed | W25: Not confirmed | X25: Not confirmed | Y25: Not confirmed | AA25: Not confirmed
U26: Not confirmed | V26: Not confirmed | W26: Not confirmed | X26: Not confirmed | Y26: Not confirmed | AA26: Not confirmed
U27: Not confirmed | V27: Not confirmed | W27: Not confirmed | X27: Not confirmed | Y27: Not confirmed | AA27: Not confirmed
U28: Not confirmed | V28: Not confirmed | W28: Not confirmed | X28: Not confirmed | Y28: Not confirmed | AA28: Not confirmed
... U104: Not confirmed | V104: Not confirmed | W104: Not confirmed | X104: Not confirmed | Y104: Not confirmed | AA104: Not confirmed

Sheet Relocation Budget
A1: Lagos / Ogun Relocation Budget
A2: Editable planning estimates in NGN — all existing estimates are illustrative placeholders, NOT confirmed market prices. Replace with current quotes for the exact location and accommodation.
A4: Expense category | B4: Low estimate (₦/month) | C4: Moderate estimate (₦/month) | D4: High estimate (₦/month) | E4: Your chosen estimate (₦/month) | F4: Notes | G4: Type
A5: Accommodation | B5: 50000 | C5: 100000 | D5: 180000 | E5: 100000 | F5: Illustrative only. If free accommodation is confirmed for all six months, enter 0 in column E. | G5: Monthly
A6: Feeding | B6: 50000 | C6: 80000 | D6: 120000 | E6: 80000 | F6: Groceries and meals | G6: Monthly
A7: Transportation | B7: 20000 | C7: 35000 | D7: 60000 | E7: 35000 | F7: Commute to placement office | G7: Monthly
A8: Data and airtime | B8: 8000 | C8: 12000 | D8: 20000 | E8: 12000 | F8: Connectivity | G8: Monthly
A9: Personal expenses | B9: 10000 | C9: 20000 | D9: 35000 | E9: 20000 | F9: Toiletries and miscellaneous | G9: Monthly
A10: Electricity | B10: 5000 | C10: 10000 | D10: 18000 | E10: 10000 | F10: Share of electricity / utilities | G10: Monthly
A11: Emergency savings | B11: 10000 | C11: 15000 | D11: 25000 | E11: 15000 | F11: Monthly reserve | G11: Monthly
A12: Initial accommodation deposit | B12: 100000 | C12: 200000 | D12: 350000 | E12: 200000 | F12: One-time setup cost only; confirm deposit, agency and legal fees. | G12: One-off
A13: Relocation expenses | B13: 25000 | C13: 50000 | D13: 80000 | E13: 50000 | F13: One-time travel / moving / setup cost; obtain a quote. | G13: One-off
A15: Monthly stipend amount (₦) | E15: 0
A16: Placement duration (months) | E16: 6
A18: Accommodation confirmed for all six months? | E18: Not confirmed
A19: Monthly stipend confirmed? | E19: Not confirmed
A20: Total funding available for relocation (₦) | E20: 0
A21: Final decision | E21: Pending confirmation
A22: Decision notes | E22: Confirm written offer, start/end dates, exact office location, accommodation conditions and payment schedule before relocating.
A25: Summary
A26: Total monthly expenses | B26: =SUM(E5:E11) -> 272000
A27: Total one-time setup costs | B27: =SUM(E12:E13) -> 250000
A28: Total six-month expenses | B28: =B26*E16+B27 -> 1882000
A29: Total stipend over placement | B29: =E15*E16 -> 0
A30: Total resources available | B30: =E20+B29 -> 0
A31: Funding shortfall | B31: =MAX(0,B28-B30) -> 1882000
A32: Funds remaining after six months | B32: =MAX(0,B30-B28) -> 0
A33: Monthly amount remaining after expenses | B33: =E15-B26 -> -272000
A34: Can I realistically afford this placement? | B34: =IF(OR(E18="Not confirmed",E19="Not confirmed"),"NO – confirm accommodation and stipend first",IF(AND(OR(E18="Yes",AND(E18="No",E5>0)),OR(E19="Yes",E19="No"),B30>=B28),"Potentially affordable – verify all terms in writing","NO – funding / accommodation plan is insufficient")) -> NO – confirm accommodation and stipend first
A36: Important relocation rule
A37: Do not relocate based on an estimated stipend or verbal promise. Treat the placement as not affordable until accommodation coverage (or a realistic paid accommodation budget), stipend status, total available funding and six-month terms are confirmed in writing. A zero accommodation cost is acceptable only when free accommodation for the full placement is confirmed.

Sheet Document Checklist
A1: Application Document Checklist
A2: Prepare core documents early. Some items are only required when requested by OAU or the specific organisation.
A4: Document | B4: Required / conditional | C4: Completion status | D4: Date completed | E4: File location / link | F4: Notes
A5: Updated CV | B5: Core | C5: Not Started | F5: Tailor summary and skills to analytics / BI / business roles.
A6: SIWES application letter | B6: Core | C6: Not Started | F6: State six-month availability and proposed April 2027 start.
A7: OAU introduction letter | B7: Core | C7: Not Started | F7: Request from the appropriate university office.
A8: HOD recommendation / endorsement | B8: As requested / placement requirement | C8: Not Started | F8: Seplat's published scheme requires SIWES letter issued by HOD addressed to Seplat HR.
A9: Student ID | B9: Core | C9: Not Started | F9: Keep a clear scanned copy.
A10: SIWES documentation | B10: Core | C10: Not Started | F10: Logbook and institution-specific forms; confirm current OAU requirements.
A11: Academic transcript or CGPA evidence | B11: Where requested | C11: Not Started | F11: Do not send unless requested or application instructions require it.
A12: Portfolio / GitHub links | B12: Recommended | C12: Not Started | F12: Include Power BI, Excel, SQL, Python, analytics or business projects.
A13: Passport photograph | B13: Where requested | C13: Not Started | F13: Use only if requested by employer.
A14: Other company-specific documents | B14: Where requested | C14: Not Started | F14: Record exact instructions and submission format.

Sheet Dashboard
A1: Mercy's SIWES / IT Placement Dashboard – 2027
A2: Live summary: counts are based on actual dates / confirmed dropdown fields in Application Tracker. Update the tracker to refresh these figures.
A4: Total organisations shortlisted | E4: Companies contacted (date recorded)
A5: =COUNTA('Company Shortlist'!B5:B16) -> 12 | E5: =COUNTIF('Application Tracker'!F5:F104,">0") -> 0
A7: Applications submitted (date recorded) | E7: Responses received
A8: =COUNTIF('Application Tracker'!G5:G104,">0") -> 0 | E8: =COUNTIF('Application Tracker'!J5:J104,"Yes") -> 0
A10: Interviews scheduled (date recorded) | E10: Offers received
A11: =COUNTIF('Application Tracker'!K5:K104,">0") -> 0 | E11: =COUNTIF('Application Tracker'!Q5:Q104,"Offer Received") -> 0
A13: Accommodation confirmed | E13: Six-month placements confirmed
A14: =COUNTIF('Application Tracker'!X5:X104,"Yes") -> 0 | E14: =COUNTIF('Application Tracker'!V5:V104,"Yes") -> 0
A17: Application status | B17: Count | D17: Confirmed support / eligibility | E17: Count
A18: Not Started | B18: =COUNTIF('Application Tracker'!Q5:Q104,A18) -> 12 | D18: Accommodation | E18: =COUNTIF('Application Tracker'!X5:X104,"Yes") -> 0
A19: Researching | B19: =COUNTIF('Application Tracker'!Q5:Q104,A19) -> 0 | D19: Six-month duration | E19: =COUNTIF('Application Tracker'!V5:V104,"Yes") -> 0
A20: Contacted | B20: =COUNTIF('Application Tracker'!Q5:Q104,A20) -> 0 | D20: Official SIWES vacancy | E20: =COUNTIF('Application Tracker'!AA5:AA104,"Yes") -> 0
A21: Applied | B21: =COUNTIF('Application Tracker'!Q5:Q104,A21) -> 0
A22: Follow-up Due | B22: =COUNTIF('Application Tracker'!Q5:Q104,A22) -> 0
A23: Interviewing | B23: =COUNTIF('Application Tracker'!Q5:Q104,A23) -> 0
A24: Offer Received | B24: =COUNTIF('Application Tracker'!Q5:Q104,A24) -> 0
A25: Rejected | B25: =COUNTIF('Application Tracker'!Q5:Q104,A25) -> 0
A26: On Hold | B26: =COUNTIF('Application Tracker'!Q5:Q104,A26) -> 0
